gradle.properties
hexdoc_hierophantics/__gradle_version__.py
hexdoc_hierophantics/__init__.py
hexdoc_hierophantics/__version__.py
hexdoc_hierophantics/_hooks.py
hexdoc_hierophantics/py.typed
hexdoc_hierophantics/_export/.gitignore
hexdoc_hierophantics/_export/__init__.py
hexdoc_hierophantics/_export/generated/__init__.py
hexdoc_hierophantics/_export/generated/hierophantics.hexdoc.json
hexdoc_hierophantics/_export/generated/hierophantics.patterns.hexdoc.json
hexdoc_hierophantics/_export/generated/assets/hexcasting/patchouli_books/thehexbook/en_us/entries/greatwork/allay_imbuement.json
hexdoc_hierophantics/_export/generated/assets/hexcasting/patchouli_books/thehexbook/en_us/entries/greatwork/hierophantics.json
hexdoc_hierophantics/_export/generated/assets/hexcasting/patchouli_books/thehexbook/en_us/entries/greatwork/villager_enhancement.json
hexdoc_hierophantics/_export/generated/assets/hexcasting/patchouli_books/thehexbook/en_us/entries/items/imbuement_bed.json
hexdoc_hierophantics/_export/generated/assets/hexcasting/patchouli_books/thehexbook/en_us/entries/patterns/mind_handling.json
hexdoc_hierophantics/_export/generated/assets/hexcasting/patchouli_books/thehexbook/en_us/entries/patterns/triggers.json
hexdoc_hierophantics/_export/generated/assets/hexcasting/patchouli_books/thehexbook/en_us/entries/patterns/spells/villager_sleep.json
hexdoc_hierophantics/_export/generated/assets/hierophantics/lang/en_us.flatten.json5
hexdoc_hierophantics/_export/generated/assets/hierophantics/lang/en_us.json
hexdoc_hierophantics/_export/generated/assets/hierophantics/lang/zh_cn.flatten.json5
hexdoc_hierophantics/_export/generated/assets/hierophantics/lang/zh_cn.json
hexdoc_hierophantics/_export/generated/assets/hierophantics/models/block/edified_workstation.json
hexdoc_hierophantics/_export/generated/assets/hierophantics/models/item/edified_workstation.json
hexdoc_hierophantics/_export/generated/assets/hierophantics/models/item/flay_bed.json
hexdoc_hierophantics-1.3.5.1.0.dist-info/METADATA
hexdoc_hierophantics-1.3.5.1.0.dist-info/WHEEL
hexdoc_hierophantics-1.3.5.1.0.dist-info/entry_points.txt
hexdoc_hierophantics-1.3.5.1.0.dist-info/licenses/LICENSE
hexdoc_hierophantics-1.3.5.1.0.dist-info/RECORD
