Metadata-Version: 2.4
Name: hexdoc-hierophantics
Version: 1.3.5.1.0
Summary: An addon to Hex Casting that lets you work with extracted minds to create conditional hexes and merge villagers.
Project-URL: Homepage, https://robotgiggle.github.io/hierophantics
Project-URL: Source, https://github.com/Robotgiggle/hierophantics
Author: Robotgiggle
License-File: LICENSE
Keywords: hexdoc
Requires-Python: >=3.11
Requires-Dist: hexdoc-hexcasting~=0.11.2.1.0
Provides-Extra: dev
Requires-Dist: ruff~=0.11.13; extra == 'dev'
